odoo/addons/product_multi_code/README.rst
odoo/addons/product_multi_code/__init__.py
odoo/addons/product_multi_code/__manifest__.py
odoo/addons/product_multi_code/hooks.py
odoo/addons/product_multi_code/i18n/es.po
odoo/addons/product_multi_code/i18n/it.po
odoo/addons/product_multi_code/i18n/product_multi_code.pot
odoo/addons/product_multi_code/models/__init__.py
odoo/addons/product_multi_code/models/product_default_code.py
odoo/addons/product_multi_code/models/product_product.py
odoo/addons/product_multi_code/models/product_template.py
odoo/addons/product_multi_code/readme/CONTRIBUTORS.md
odoo/addons/product_multi_code/readme/DESCRIPTION.md
odoo/addons/product_multi_code/readme/USAGE.md
odoo/addons/product_multi_code/security/group.xml
odoo/addons/product_multi_code/security/ir.model.access.csv
odoo/addons/product_multi_code/static/description/icon.png
odoo/addons/product_multi_code/static/description/index.html
odoo/addons/product_multi_code/tests/__init__.py
odoo/addons/product_multi_code/tests/test_product_multi_code.py
odoo/addons/product_multi_code/views/product_template_views.xml
odoo/addons/product_multi_code/views/product_views.xml
odoo_addon_product_multi_code-17.0.1.1.0.2.dist-info/METADATA
odoo_addon_product_multi_code-17.0.1.1.0.2.dist-info/WHEEL
odoo_addon_product_multi_code-17.0.1.1.0.2.dist-info/top_level.txt
odoo_addon_product_multi_code-17.0.1.1.0.2.dist-info/RECORD
